texas_holdem_poker/__init__.py
texas_holdem_poker/dealer.py
texas_holdem_poker/hand_rank.py
texas_holdem_poker/holdem_game.py
texas_holdem_poker/poker_ai.py
texas_holdem_poker/poker_card.py
texas_holdem_poker/win_rate_calculator.py
texas_holdem_poker-0.1.8.dist-info/METADATA
texas_holdem_poker-0.1.8.dist-info/WHEEL
texas_holdem_poker-0.1.8.dist-info/top_level.txt
texas_holdem_poker-0.1.8.dist-info/RECORD
