Metadata-Version: 2.1
Name: texas-holdem-poker
Version: 0.1.8
Summary: a command-line-interacted texas holdem poker game, also include a real-time winning-rate calculator
Home-page: 
Author: ray.ping
Author-email: 342099577@qq.com
License: MIT
